engineering_session_packaging-0.0.3.data/scripts/run_app
example/__about__.py
example/__init__.py
example/app.py
example/util.py
example/bin/__init__.py
example/bin/run_app
example/submodule/__init__.py
example/submodule/util.py
example/submodule/subsubmodule/__init__.py
example/submodule/subsubmodule/util.py
engineering_session_packaging-0.0.3.dist-info/METADATA
engineering_session_packaging-0.0.3.dist-info/WHEEL
engineering_session_packaging-0.0.3.dist-info/top_level.txt
engineering_session_packaging-0.0.3.dist-info/RECORD
