Metadata-Version: 2.1
Name: engineering-session-packaging
Version: 0.0.3
Summary: test project to illustrate some python packaging
Author: NieuweNils
Author-email: noneofyour@business.com
Classifier: Programming Language :: Python :: 3
Classifier: Operating System :: OS Independent
Requires-Python: >=3.11.3
Requires-Dist: uwsgi ==2.0.*
Provides-Extra: test
Requires-Dist: pytest ; extra == 'test'
